LICENSE
README.md
setup.py
triangle/__init__.py
triangle/triangle1.py
triangle/triangle2.py
triangle_yyh.egg-info/PKG-INFO
triangle_yyh.egg-info/SOURCES.txt
triangle_yyh.egg-info/dependency_links.txt
triangle_yyh.egg-info/top_level.txt