Metadata-Version: 2.1
Name: triangle-yyh
Version: 1.0
Summary: test_pypi
Home-page: UNKNOWN
Author: yyh
Author-email: 1807875605@qq.com
License: UNKNOWN
Platform: UNKNOWN
Classifier: Programming Language :: Python :: 3
Classifier: License :: OSI Approved :: MIT License
Classifier: Operating System :: OS Independent
License-File: LICENSE
